{"files":{"packages/permissions/dist":{"size":0,"mtime_nanos":0,"mode":0,"is_dir":true},"packages/permissions/.turbo/turbo-build.log":{"size":60,"mtime_nanos":1782959983930995900,"mode":420,"is_dir":false},"packages/permissions/dist/index.js":{"size":176,"mtime_nanos":1782959983415062700,"mode":420,"is_dir":false},"packages/permissions/dist/index.d.ts":{"size":110,"mtime_nanos":1782959983425561200,"mode":420,"is_dir":false}},"order":["packages/permissions/.turbo/turbo-build.log","packages/permissions/dist","packages/permissions/dist/index.d.ts","packages/permissions/dist/index.js"]}